neuroscout_cli/__init__.py
neuroscout_cli/cli.py
neuroscout_cli/commands/__init__.py
neuroscout_cli/commands/base.py
neuroscout_cli/commands/get.py
neuroscout_cli/commands/run.py
neuroscout_cli/commands/upload.py
neuroscout_cli/tools/__init__.py
neuroscout_cli/tools/convert.py
neuroscout_cli-0.6.5.dist-info/LICENSE
neuroscout_cli-0.6.5.dist-info/METADATA
neuroscout_cli-0.6.5.dist-info/WHEEL
neuroscout_cli-0.6.5.dist-info/entry_points.txt
neuroscout_cli-0.6.5.dist-info/top_level.txt
neuroscout_cli-0.6.5.dist-info/RECORD
